common/__init__.py
common/decorators.py
common/descriptors.py
common/errors.py
common/metaclasses.py
common/utils.py
common/variables.py
server/__init__.py
server/add_user.py
server/config_window.py
server/core.py
server/database.py
server/main_window.py
server/remove_user.py
server/stat_window.py
unit_tests/__init__.py
unit_tests/test_client.py
unit_tests/test_server.py
unit_tests/test_utils.py
mess_serverVAG-0.0.1.dist-info/METADATA
mess_serverVAG-0.0.1.dist-info/WHEEL
mess_serverVAG-0.0.1.dist-info/top_level.txt
mess_serverVAG-0.0.1.dist-info/RECORD
